IO/IO.py
IO/__init__.py
IO/folder.py
IO/h5.py
IO/inrimage.py
IO/klb.py
IO/spatial_image.py
IO/tif.py
registrationtools/__init__.py
registrationtools/spatial_registration.py
registrationtools/time_registration.py
registrationtools/utils.py
registrationtools/_tests/test_spatial_reg.py
registrationtools/_tests/test_time_reg.py
registrationtools/data/JSON_spatial/test1.json
registrationtools/data/JSON_time/test1.json
registrationtools/data/JSON_time/test2.json
registrationtools/data/JSON_time/test3.json
registrationtools/data/JSON_time/test4.json
registrationtools/data/images/t0.tiff
registrationtools/data/images/t1.tiff
registrationtools/data/images/t2.tiff
registrationtools/data/images/t3.tiff
registrationtools/data/images/t4.tiff
registrationtools/data/images/t5.tiff
3d_registration-0.5.3.dist-info/METADATA
3d_registration-0.5.3.dist-info/WHEEL
3d_registration-0.5.3.dist-info/entry_points.txt
3d_registration-0.5.3.dist-info/top_level.txt
3d_registration-0.5.3.dist-info/RECORD
