Metadata-Version: 2.4
Name: 3D-registration
Version: 0.5.3
Summary: Some scripts to register images in space and time
Author-email: Léo Guignard <leo.guignard@univ-amu.fr>
Maintainer-email: Léo Guignard <leo.guignard@univ-amu.fr>
License-Expression: MIT
Project-URL: Bug Tracker, https://github.com/GuignardLab/registration-tools/issues
Project-URL: Documentation, https://github.com/GuignardLab/registration-tools#README.md
Project-URL: Source Code, https://github.com/GuignardLab/registration-tools
Project-URL: User Support, https://github.com/GuignardLab/registration-tools/issues
Classifier: Development Status :: 4 - Beta
Classifier: Intended Audience :: Developers
Classifier: Operating System :: OS Independent
Classifier: Programming Language :: Python
Classifier: Programming Language :: Python :: 3
Classifier: Programming Language :: Python :: 3 :: Only
Classifier: Programming Language :: Python :: 3.10
Classifier: Programming Language :: Python :: 3.11
Classifier: Programming Language :: Python :: 3.12
Classifier: Programming Language :: Python :: 3.13
Requires-Python: >=3.10
Requires-Dist: numpy
Requires-Dist: scipy
Requires-Dist: statsmodels
Requires-Dist: h5py
Requires-Dist: tifffile
Requires-Dist: importlib-resources
Requires-Dist: matplotlib
Requires-Dist: transforms3d
Requires-Dist: ensure
